video_pyker/__init__.py
video_pyker/__main__.py
video_pyker/game.py
video_pyker/main.py
video_pyker/screen.py
video_pyker-1.0.1.dist-info/LICENSE.md
video_pyker-1.0.1.dist-info/METADATA
video_pyker-1.0.1.dist-info/WHEEL
video_pyker-1.0.1.dist-info/entry_points.txt
video_pyker-1.0.1.dist-info/top_level.txt
video_pyker-1.0.1.dist-info/RECORD
