Metadata-Version: 2.1
Name: video-pyker
Version: 1.0.1
Summary: A little terminal game for Jacks-or-Better Video Poker.
Author-email: Charlie Morris <charliertm1@gmail.com>
License: Copyright 2022 Charlie Morris        
Project-URL: Homepage, https://github.com/charliertm/video-pyker
Keywords: poker,game,video-poker
Classifier: License :: OSI Approved :: MIT License
Classifier: Programming Language :: Python
Classifier: Programming Language :: Python :: 3
Requires-Python: >=3.10.2
License-File: LICENSE.md
Requires-Dist: simple-term-menu (>=1.4.1)
Requires-Dist: colorama (==0.4.4)
Provides-Extra: dev
Requires-Dist: bumpver ; extra == 'dev'
